bioio_ome_tiff/__init__.py
bioio_ome_tiff/py.typed
bioio_ome_tiff/reader.py
bioio_ome_tiff/reader_metadata.py
bioio_ome_tiff/utils.py
bioio_ome_tiff/tests/__init__.py
bioio_ome_tiff/tests/conftest.py
bioio_ome_tiff/tests/test_reader.py
bioio_ome_tiff/tests/writers/__init__.py
bioio_ome_tiff/tests/writers/test_ome_tiff_writer.py
bioio_ome_tiff/writers/__init__.py
bioio_ome_tiff/writers/ome_tiff_writer.py
bioio_ome_tiff_fork_by_bugra-0.0.1b2.dist-info/licenses/LICENSE
scripts/TEST_RESOURCES_HASH.txt
scripts/download_test_resources.py
scripts/upload_test_resources.py
bioio_ome_tiff_fork_by_bugra-0.0.1b2.dist-info/METADATA
bioio_ome_tiff_fork_by_bugra-0.0.1b2.dist-info/WHEEL
bioio_ome_tiff_fork_by_bugra-0.0.1b2.dist-info/entry_points.txt
bioio_ome_tiff_fork_by_bugra-0.0.1b2.dist-info/top_level.txt
bioio_ome_tiff_fork_by_bugra-0.0.1b2.dist-info/RECORD
