Metadata-Version: 2.4
Name: bioio-ome-tiff-fork-by-bugra
Version: 0.0.1b2
Summary: A fork of bioio-ome-tiff project.
License: MIT License
Project-URL: Homepage, https://github.com/Euro-BioImaging/bioio-ome-tiff/tree/updated
Classifier: Development Status :: 4 - Beta
Classifier: Natural Language :: English
Classifier: Programming Language :: Python :: 3.11
Classifier: Programming Language :: Python :: 3.12
Classifier: Programming Language :: Python :: 3.13
Requires-Python: >=3.11
License-File: LICENSE
Requires-Dist: bioio-base>=1.4.0
Requires-Dist: dask[array]>=2021.4.1
Requires-Dist: fsspec>=2022.8.0
Requires-Dist: imagecodecs>=2020.5.30
Requires-Dist: numpy>=1.21
Requires-Dist: ome-types[lxml]>=0.4.0
Requires-Dist: pydantic>=1.10.0
Requires-Dist: PyYAML>=6.0
Requires-Dist: xarray>=0.16.1
Requires-Dist: xmlschema
Provides-Extra: lint
Requires-Dist: pre-commit>=2.20.0; extra == "lint"
Provides-Extra: test
Requires-Dist: coverage>=5.1; extra == "test"
Requires-Dist: pytest>=5.4.3; extra == "test"
Requires-Dist: pytest-cov>=2.9.0; extra == "test"
Requires-Dist: pytest-raises>=0.11; extra == "test"
Requires-Dist: quilt3; extra == "test"
Requires-Dist: types-PyYAML>=6.0.12.9; extra == "test"
Dynamic: license-file
